Workbook

Sheet Unit Economics
A1: Digital product: unit economics
A2: Blue cells on yellow are inputs. Everything else is a formula. Example values are placeholders, not research.
A4: INPUTS: per sale
A5: Price | B5: 19 | C5: Common range $15-25 for a bundle (seller blogs, unverified)
A6: Platform fee, percent of price | B6: 0.1 | C6: ASSUMPTION: varies by platform (Gumroad, Etsy, Payhip...). Check yours
A7: Payment fee, percent | B7: 0.029 | C7: Typical card rate; check your processor
A8: Payment fee, fixed per sale | B8: 0.3 | C8: Typical; check your processor
A9: Refund reserve, percent of price | B9: 0.05 | C9: ASSUMPTION; replace with actual rate
A10: Other cost per sale (delivery, support time value) | B10: 0 | C10: Usually near zero for digital
A12: INPUTS: fixed and paid-ad costs
A13: Fixed costs for the test (domain, tools, store) | B13: 100 | C13: Plan cap
A14: Paid-ad budget (only if Phase 3 is unlocked) | B14: 200 | C14: Plan cap; spend only after 10+ organic sales
A15: Expected cost per click (CPC) | B15: 0.8 | C15: ASSUMPTION; no verified benchmark found
A16: Click-to-purchase conversion, cold traffic | B16: 0.015 | C16: ASSUMPTION; cold traffic to a low-priced product is often low
A18: OUTPUTS
A19: Platform fee per sale | B19: =B5*B6
A20: Payment fees per sale | B20: =B5*B7+B8
A21: Refund reserve per sale | B21: =B5*B9
A22: Net contribution per sale (M) | B22: =B5-B19-B20-B21-B10 | C22: Break-even cost per sale
A23: Net margin % | B23: =IF(B5>0,B22/B5,0)
A24: Sales needed to cover fixed costs | B24: =IF(B22>0,B13/B22,0)
A25: Max cost per sale for breakeven (CPA = M) | B25: =B22
A26: Max cost per sale to count as a pass (0.7 x M) | B26: =0.7*B22
A27: Expected cold-ad cost per sale (CPC / conversion) | B27: =IF(B16>0,B15/B16,0)
A28: Cold ads viable at these inputs? | B28: =IF(B27<=B26,"YES","NO: use organic / warm audiences only") | C28: Plan rule: ads need cost per sale at or below 0.7 x M
A29: Required conversion for ads to hit 0.7 x M | B29: =IF(B26>0,B15/B26,0)

Sheet Funnel
A1: Content-first funnel scenarios (8 weeks)
A2: Views -> email signups -> buyers. All rates are assumptions to be replaced by your real numbers.
A4: Assumption | B4: Low | C4: Base | D4: High
A5: Weekly content views | B5: 2000 | C5: 5000 | D5: 15000
A6: Weeks of posting before launch | B6: 4 | C6: 4 | D6: 4
A7: View-to-email-signup rate | B7: 0.005 | C7: 0.01 | D7: 0.02
A8: List-to-buyer rate at launch | B8: 0.02 | C8: 0.04 | D8: 0.08
A9: Weeks of sales after launch | B9: 4 | C9: 4 | D9: 4
A10: Ongoing weekly buyers per 1,000 list members | B10: 1 | C10: 2 | D10: 4
A12: Results
A13: Email list at launch | B13: =B5*B6*B7 | C13: =C5*C6*C7 | D13: =D5*D6*D7
A14: Launch buyers | B14: =B13*B8 | C14: =C13*C8 | D14: =D13*D8
A15: Ongoing buyers after launch | B15: =B13/1000*B10*B9 | C15: =C13/1000*C10*C9 | D15: =D13/1000*D10*D9
A16: Total buyers (8 weeks) | B16: =B14+B15 | C16: =C14+C15 | D16: =D14+D15
A17: Revenue | B17: =B16*'Unit Economics'!$B$5 | C17: =C16*'Unit Economics'!$B$5 | D17: =D16*'Unit Economics'!$B$5
A18: Net contribution (buyers x M) | B18: =B16*'Unit Economics'!$B$22 | C18: =C16*'Unit Economics'!$B$22 | D18: =D16*'Unit Economics'!$B$22
A19: Net after fixed costs | B19: =B18-'Unit Economics'!$B$13 | C19: =C18-'Unit Economics'!$B$13 | D19: =D18-'Unit Economics'!$B$13
A20: Meets plan PASS (30+ buyers, 200+ list)? | B20: =IF(AND(B16>=30,B13>=200),"YES","NO") | C20: =IF(AND(C16>=30,C13>=200),"YES","NO") | D20: =IF(AND(D16>=30,D13>=200),"YES","NO")
A22: Even the High case is only a guess. The point is to see which rate you most need to beat, then measure it in the first 4 weeks.

Sheet Income Targets
A1: What a monthly income target needs
A2: Sales per month = target / M. List size assumes a monthly buyer rate on the list.
A4: Monthly buyer rate on email list (buyers per 1,000 per month) | B4: 8 | C4: ASSUMPTION; replace with measured
A6: Monthly net target ($) | B6: Sales / month | C6: Sales / day | D6: List size needed | E6: Gross revenue / month
A7: 500 | B7: =IF('Unit Economics'!$B$22>0,A7/'Unit Economics'!$B$22,0) | C7: =B7/30 | D7: =IF($B$4>0,B7/$B$4*1000,0) | E7: =B7*'Unit Economics'!$B$5
A8: 1000 | B8: =IF('Unit Economics'!$B$22>0,A8/'Unit Economics'!$B$22,0) | C8: =B8/30 | D8: =IF($B$4>0,B8/$B$4*1000,0) | E8: =B8*'Unit Economics'!$B$5
A9: 3000 | B9: =IF('Unit Economics'!$B$22>0,A9/'Unit Economics'!$B$22,0) | C9: =B9/30 | D9: =IF($B$4>0,B9/$B$4*1000,0) | E9: =B9*'Unit Economics'!$B$5
A10: 5000 | B10: =IF('Unit Economics'!$B$22>0,A10/'Unit Economics'!$B$22,0) | C10: =B10/30 | D10: =IF($B$4>0,B10/$B$4*1000,0) | E10: =B10*'Unit Economics'!$B$5
A11: 10000 | B11: =IF('Unit Economics'!$B$22>0,A11/'Unit Economics'!$B$22,0) | C11: =B11/30 | D11: =IF($B$4>0,B11/$B$4*1000,0) | E11: =B11*'Unit Economics'!$B$5
A13: One product only. Real businesses add more products and a higher-priced offer (course, coaching) to reach the top rows.

Sheet Test Log
A1: 8-week test log and kill-rule monitor
A2: Enter weekly numbers in blue/yellow columns only. Week 1 holds an example row: overwrite it.
D3: Kill rule | H3: Status
A4: Current week (1-8) | B4: 1 | C4: Update weekly | D4: 1. Cash spent at or above $300 | H4: =IF(B12>=300,"KILL","ok")
A5: Launch week (week the product goes on sale) | B5: 5 | C5: Plan: week 5 | D5: 2. Week 3+, 12+ posts, under 25 signups | H5: =IF(AND(B4>=3,B6>=12,B8<25),"KILL","ok")
A6: Posts published to date | B6: =SUMIFS(B17:B24,A17:A24,"<="&B4) | D6: 3. 3 weeks after launch, 100+ list, under 5 sales | H6: =IF(AND(B4>=B5+3,B7>=100,B9<5),"KILL","ok")
A7: Email list size (latest entered) | B7: =IFERROR(INDEX(D17:D24,MATCH(B4,A17:A24,0)),0) | D7: 4. Refund rate above 10% (10+ sales) | H7: =IF(AND(B9>=10,B13>0.1),"KILL","ok")
A8: Email signups to date | B8: =SUMIFS(C17:C24,A17:A24,"<="&B4) | D8: 5. Ads before 10 organic sales | H8: =IF(AND(B11>0,B9<10),"KILL","ok")
A9: Paying customers to date | B9: =SUMIFS(E17:E24,A17:A24,"<="&B4) | D9: Manual: accuracy complaints, platform strikes, ad-account warnings, or claims you can't back up. Pause and note it.
A10: Refunded orders to date | B10: =SUMIFS(F17:F24,A17:A24,"<="&B4) | D10: Rule 6: the test ends after week 8.
A11: Ad spend to date | B11: =SUMIFS(G17:G24,A17:A24,"<="&B4)
A12: Cash spent to date (fixed + ads) | B12: =B11+'Unit Economics'!B13
A13: Refund rate | B13: =IF(B9>0,B10/B9,0)
A14: Net profit to date (customers x M - ads - fixed) | B14: =B9*'Unit Economics'!$B$22-B11-'Unit Economics'!B13
A15: Week-8 verdict | B15: =IF(COUNTIF(H4:H8,"KILL")>0,"KILLED",IF(B4<8,"IN PROGRESS",IF(AND(B9>=30,B7>=200,B13<0.08,B14>0),"PASS",IF(B9>=10,"INCONCLUSIVE","FAIL"))))
A16: Week | B16: Posts published | C16: New email signups | D16: Email list size | E16: Paying customers | F16: Refunded orders | G16: Ad spend ($) | H16: Views (all posts) | I16: Notes
A17: 1 | B17: 4 | C17: 12 | D17: 12 | E17: 0 | F17: 0 | G17: 0 | H17: 1500 | I17: Example row: replace
A18: 2
A19: 3
A20: 4
A21: 5
A22: 6
A23: 7
A24: 8

Sheet Notes
A1: Assumptions and sources
A3: Source: DIGITAL_PRODUCT_TEST_PLAN.md in this repo (gates, phases, kill rules, thresholds). Written before any data.
A4: All example numbers (price $19, fees, CPC $0.80, conversion 1.5%, funnel rates) are placeholders chosen by the author. None were measured.
A5: Price range $15-25 for a grade/subject bundle comes from seller blogs (Etsy guides), not verified sales data.
A6: Market size (about 3.0-3.7M US homeschoolers) comes from secondary roundups; verify with NCES NHES and the Johns Hopkins Homeschool Hub.
A7: Platform fee varies a lot by platform. Update it for the one you choose.
A8: Cold-ad cost per click and conversion for education products were not found in any benchmark. Measure them.
A9: Taxes (including sales tax on digital goods in some states), and your time, are not modelled.
A10: Tabs: Unit Economics (inputs, margin, ad viability) | Funnel (low/base/high) | Income Targets | Test Log (kill rules).
